LICENSE.txt
README.txt
setup.py
SimpleEconomy/__init__.py
SimpleEconomy.egg-info/PKG-INFO
SimpleEconomy.egg-info/SOURCES.txt
SimpleEconomy.egg-info/dependency_links.txt
SimpleEconomy.egg-info/requires.txt
SimpleEconomy.egg-info/top_level.txt