Metadata-Version: 2.1
Name: SimpleEconomy
Version: 2.3
Summary: Very easy to use discord.py economy creator
Home-page: UNKNOWN
Author: MrStretch
Author-email: mrstretchd@gmail.com
License: MIT
Keywords: Ecomomy,Simple,discord.py
Platform: UNKNOWN
Classifier: Development Status :: 5 - Production/Stable
Classifier: Intended Audience :: Education
Classifier: Operating System :: Microsoft :: Windows :: Windows 10
Classifier: License :: OSI Approved :: MIT License
Classifier: Programming Language :: Python :: 3
License-File: LICENSE.txt
